converter.py
pyuic5_tool-0.0.1.dist-info/LICENSE
pyuic5_tool-0.0.1.dist-info/METADATA
pyuic5_tool-0.0.1.dist-info/WHEEL
pyuic5_tool-0.0.1.dist-info/top_level.txt
pyuic5_tool-0.0.1.dist-info/RECORD
