Metadata-Version: 2.1
Name: pyuic5-tool
Version: 0.0.1
Summary: An automation tool for pyuic5 command
Home-page: https://github.com/Abdelatief/Pyuic5-Tool
Author: Abdelrahman Ahmed
Author-email: abdelatief99@gmail.com
License: UNKNOWN
Platform: UNKNOWN
Classifier: Programming Language :: Python :: 3
Classifier: License :: OSI Approved :: MIT License
Classifier: Operating System :: OS Independent
Requires-Python: >=3.6
